django_dbq_exports/__init__.py
django_dbq_exports/models.py
django_dbq_exports/serializers.py
django_dbq_exports/tasks.py
django_dbq_exports/urls.py
django_dbq_exports/views.py
django_dbq_exports/__pycache__/__init__.cpython-37.pyc
django_dbq_exports/__pycache__/__init__.cpython-38.pyc
django_dbq_exports/__pycache__/boot_django.cpython-38.pyc
django_dbq_exports/__pycache__/models.cpython-37.pyc
django_dbq_exports/__pycache__/models.cpython-38.pyc
django_dbq_exports/__pycache__/serializers.cpython-37.pyc
django_dbq_exports/__pycache__/serializers.cpython-38.pyc
django_dbq_exports/__pycache__/tasks.cpython-37.pyc
django_dbq_exports/__pycache__/tasks.cpython-38.pyc
django_dbq_exports/__pycache__/urls.cpython-37.pyc
django_dbq_exports/__pycache__/urls.cpython-38.pyc
django_dbq_exports/__pycache__/views.cpython-37.pyc
django_dbq_exports/__pycache__/views.cpython-38.pyc
django_dbq_exports/migrations/0001_initial.py
django_dbq_exports/migrations/0002_auto_20200723_0723.py
django_dbq_exports/migrations/__init__.py
django_dbq_exports/migrations/__pycache__/0001_initial.cpython-37.pyc
django_dbq_exports/migrations/__pycache__/0001_initial.cpython-38.pyc
django_dbq_exports/migrations/__pycache__/0002_auto_20200720_1053.cpython-38.pyc
django_dbq_exports/migrations/__pycache__/0002_auto_20200723_0723.cpython-37.pyc
django_dbq_exports/migrations/__pycache__/0002_auto_20200723_0723.cpython-38.pyc
django_dbq_exports/migrations/__pycache__/0003_auto_20200720_1142.cpython-38.pyc
django_dbq_exports/migrations/__pycache__/0004_auto_20200720_1151.cpython-38.pyc
django_dbq_exports/migrations/__pycache__/__init__.cpython-37.pyc
django_dbq_exports/migrations/__pycache__/__init__.cpython-38.pyc
django_db_queue_exports-0.0.3.dist-info/LICENSE
django_db_queue_exports-0.0.3.dist-info/METADATA
django_db_queue_exports-0.0.3.dist-info/WHEEL
django_db_queue_exports-0.0.3.dist-info/top_level.txt
django_db_queue_exports-0.0.3.dist-info/RECORD
