Metadata-Version: 2.1
Name: django-db-queue-exports
Version: 0.0.3
Summary: An extension to django-db-queue for monitoring long running jobs
Home-page: https://www.dabapps.com/
Author: DabApps
Author-email: engineering@dabapps.com
License: BSD
Project-URL: Source, https://github.com/dabapps/django-db-queue-exports
Platform: UNKNOWN
Requires-Dist: django-db-queue (==1.3.0)
Requires-Dist: django-model-utils (==2.3.1)
Requires-Dist: django-uuidfield (==0.5.0)
Requires-Dist: jsonfield (==2.0.2)
Requires-Dist: Django (>=2.2)
Requires-Dist: djangorestframework (==3.9.2)
